AUTHORS.rst
CONTRIBUTING.rst
HISTORY.rst
LICENSE
LICENSE_AHK.txt
MANIFEST.in
README.rst
setup.cfg
setup.py
ahk_bin.egg-info/PKG-INFO
ahk_bin.egg-info/SOURCES.txt
ahk_bin.egg-info/dependency_links.txt
ahk_bin.egg-info/not-zip-safe
ahk_bin.egg-info/requires.txt
ahk_bin.egg-info/top_level.txt
ahkbin/__init__.py
ahkbin/ahkbin.py
ahkbin/ahk/AutoHotkey.exe
tests/__init__.py
tests/test_ahkbin.py