Metadata-Version: 1.1
Name: ahk-bin
Version: 0.0.5
Summary: A python package that bundled with workable AutoHotkey binary which could works for 'ahk' package 
Home-page: https://github.com/starofrainnight/ahk-bin
Author: Hong-She Liang
Author-email: starofrainnight@gmail.com
License: GNU General Public License v2 (GPLv2)
Keywords: ahkbin,ahk-bin
Platform: UNKNOWN
Classifier: Development Status :: 2 - Pre-Alpha
Classifier: Intended Audience :: Developers
Classifier: License :: OSI Approved :: GNU General Public License v2 (GPLv2)
Classifier: Programming Language :: Python :: 3
Classifier: Programming Language :: Python :: 3.5
Classifier: Programming Language :: Python :: 3.6
Classifier: Programming Language :: Python :: 3.7
